aerisapisdk/__init__.py
aerisapisdk/aeradminsdk.py
aerisapisdk/aerframesdk.py
aerisapisdk/aerisconfig.py
aerisapisdk/aerisutils.py
aerisapisdk/aertrafficsdk.py
aerisapisdk/cli.py
aerisapisdk/exceptions.py
aerisapisdk-0.1.5.dist-info/entry_points.txt
aerisapisdk-0.1.5.dist-info/LICENSE
aerisapisdk-0.1.5.dist-info/WHEEL
aerisapisdk-0.1.5.dist-info/METADATA
aerisapisdk-0.1.5.dist-info/RECORD
